odoo/addons/website_event_crm_invitation/README.rst
odoo/addons/website_event_crm_invitation/__init__.py
odoo/addons/website_event_crm_invitation/__manifest__.py
odoo/addons/website_event_crm_invitation/data/ir_cron_data.xml
odoo/addons/website_event_crm_invitation/data/mail_template_data.xml
odoo/addons/website_event_crm_invitation/i18n/es.po
odoo/addons/website_event_crm_invitation/i18n/it.po
odoo/addons/website_event_crm_invitation/i18n/website_event_crm_invitation.pot
odoo/addons/website_event_crm_invitation/models/__init__.py
odoo/addons/website_event_crm_invitation/models/crm_lead.py
odoo/addons/website_event_crm_invitation/models/crm_stage.py
odoo/addons/website_event_crm_invitation/models/event_type.py
odoo/addons/website_event_crm_invitation/readme/CONFIGURE.md
odoo/addons/website_event_crm_invitation/readme/CONTRIBUTORS.md
odoo/addons/website_event_crm_invitation/readme/DESCRIPTION.md
odoo/addons/website_event_crm_invitation/readme/INSTALL.md
odoo/addons/website_event_crm_invitation/readme/USAGE.md
odoo/addons/website_event_crm_invitation/static/description/icon.png
odoo/addons/website_event_crm_invitation/static/description/index.html
odoo/addons/website_event_crm_invitation/tests/__init__.py
odoo/addons/website_event_crm_invitation/tests/test_website_event_crm.py
odoo/addons/website_event_crm_invitation/views/crm_lead_view.xml
odoo/addons/website_event_crm_invitation/views/crm_stage_view.xml
odoo/addons/website_event_crm_invitation/wizards/__init__.py
odoo/addons/website_event_crm_invitation/wizards/mail_compose_message.py
odoo_addon_website_event_crm_invitation-17.0.1.0.0.2.dist-info/METADATA
odoo_addon_website_event_crm_invitation-17.0.1.0.0.2.dist-info/WHEEL
odoo_addon_website_event_crm_invitation-17.0.1.0.0.2.dist-info/top_level.txt
odoo_addon_website_event_crm_invitation-17.0.1.0.0.2.dist-info/RECORD
